tests/__init__.py
tests/test_separator.py
vokal/__init__.py
vokal/separator.py
vokal-1.0.2.dist-info/METADATA
vokal-1.0.2.dist-info/WHEEL
vokal-1.0.2.dist-info/top_level.txt
vokal-1.0.2.dist-info/RECORD
