Metadata-Version: 2.1
Name: vokal
Version: 1.0.2
Summary: A Python library for separating vocals and instruments from audio using Demucs.
Home-page: https://github.com/Meet2147/vokal
Author: Meet Jethwa
Author-email: meetjethwa3@gmail.com
License: MIT
Keywords: vocal separation,music processing,audio tools
Classifier: Development Status :: 5 - Production/Stable
Classifier: Intended Audience :: Developers
Classifier: Operating System :: OS Independent
Classifier: License :: OSI Approved :: MIT License
Classifier: Programming Language :: Python
Classifier: Programming Language :: Python :: 3
Classifier: Programming Language :: Python :: 3.7
Classifier: Programming Language :: Python :: 3.8
Classifier: Programming Language :: Python :: 3.9
Classifier: Programming Language :: Python :: 3.10
Classifier: Programming Language :: Python :: 3.11
Requires-Dist: demucs
